Workbook

Sheet Dashboard
A1: IOM PLAN VS ACHIEVED — FY 2026–27
A2: Period | B2: YTD | D2: MTD | E2: August 2026
A4: From | B4: =IF(B2="YTD",DATE(2026,4,1),IF(B2="QTD",DATE(2026,7,1),DATE(2026,8,1))) | D4: Units | E4: ₹ crore, excluding tax
A5: To | B5: 46265 | D5: Calculation | E5: Automatic when source tabs are updated
A7: Management Summary
A8: Plan / Budget | B8: =SUM(B10:B12) | C8: Achieved Awards | D8: =SUM(C10:C11) | E8: Achievement | F8: =IFERROR(D8/B8,0)
A9: Category | B9: Plan / Budget | C9: Achieved | D9: Count | E9: Achievement %
A10: Awarded IOM | B10: =SUMIFS(Contracts!$I$2:$I$10000,Contracts!$G$2:$G$10000,">="&$B$4,Contracts!$G$2:$G$10000,"<="&$B$5,Contracts!$H$2:$H$10000,1) | C10: =SUMIFS(Contracts!$J$2:$J$10000,Contracts!$G$2:$G$10000,">="&$B$4,Contracts!$G$2:$G$10000,"<="&$B$5,Contracts!$H$2:$H$10000,1) | D10: =COUNTIFS(Contracts!$G$2:$G$10000,">="&$B$4,Contracts!$G$2:$G$10000,"<="&$B$5,Contracts!$H$2:$H$10000,1) | E10: =IFERROR(C10/B10,0)
A11: Procurement | B11: =SUMIFS(Procurement!$F$2:$F$10000,Procurement!$E$2:$E$10000,">="&$B$4,Procurement!$E$2:$E$10000,"<="&$B$5) | C11: =SUMIFS(Procurement!$G$2:$G$10000,Procurement!$E$2:$E$10000,">="&$B$4,Procurement!$E$2:$E$10000,"<="&$B$5) | D11: =COUNTIFS(Procurement!$E$2:$E$10000,">="&$B$4,Procurement!$E$2:$E$10000,"<="&$B$5) | E11: =IFERROR(C11/B11,0)
A12: Balance | B12: =SUMIFS(Balance!$F$2:$F$10000,Balance!$E$2:$E$10000,">="&$B$4,Balance!$E$2:$E$10000,"<="&$B$5) | C12: 0 | D12: =COUNTIFS(Balance!$E$2:$E$10000,">="&$B$4,Balance!$E$2:$E$10000,"<="&$B$5) | E12: 0
A13: Overall | B13: =SUM(B10:B12) | C13: =SUM(C10:C12) | D13: =SUM(D10:D12) | E13: =IFERROR(C13/B13,0)
A17: TES / Non-TES Awards
A18: Classification | B18: Plan / Budget | C18: Achieved | D18: Achievement %
A19: TES | B19: =SUMIFS(Contracts!$I$2:$I$10000,Contracts!$G$2:$G$10000,">="&$B$4,Contracts!$G$2:$G$10000,"<="&$B$5,Contracts!$H$2:$H$10000,1,Contracts!$E$2:$E$10000,"TES")+SUMIFS(Procurement!$F$2:$F$10000,Procurement!$E$2:$E$10000,">="&$B$4,Procurement!$E$2:$E$10000,"<="&$B$5,Procurement!$D$2:$D$10000,"TES") | C19: =SUMIFS(Contracts!$J$2:$J$10000,Contracts!$G$2:$G$10000,">="&$B$4,Contracts!$G$2:$G$10000,"<="&$B$5,Contracts!$H$2:$H$10000,1,Contracts!$E$2:$E$10000,"TES")+SUMIFS(Procurement!$G$2:$G$10000,Procurement!$E$2:$E$10000,">="&$B$4,Procurement!$E$2:$E$10000,"<="&$B$5,Procurement!$D$2:$D$10000,"TES") | D19: =IFERROR(C19/B19,0)
A20: Non-TES | B20: =SUMIFS(Contracts!$I$2:$I$10000,Contracts!$G$2:$G$10000,">="&$B$4,Contracts!$G$2:$G$10000,"<="&$B$5,Contracts!$H$2:$H$10000,1,Contracts!$E$2:$E$10000,"Non-TES")+SUMIFS(Procurement!$F$2:$F$10000,Procurement!$E$2:$E$10000,">="&$B$4,Procurement!$E$2:$E$10000,"<="&$B$5,Procurement!$D$2:$D$10000,"Non-TES") | C20: =SUMIFS(Contracts!$J$2:$J$10000,Contracts!$G$2:$G$10000,">="&$B$4,Contracts!$G$2:$G$10000,"<="&$B$5,Contracts!$H$2:$H$10000,1,Contracts!$E$2:$E$10000,"Non-TES")+SUMIFS(Procurement!$G$2:$G$10000,Procurement!$E$2:$E$10000,">="&$B$4,Procurement!$E$2:$E$10000,"<="&$B$5,Procurement!$D$2:$D$10000,"Non-TES") | D20: =IFERROR(C20/B20,0)
A21: Overall awards include records where TES / Non-TES is not filled.
A24: BOQ and Design Dependencies — Overall Balance
A25: Team | B25: Dependency | C25: Planned Awards | D25: Recorded PTE
A26: C&B | B26: BOQ | C26: =COUNTIF(Balance!$J$2:$J$10000,"C&B - BOQ") | D26: =SUMIF(Balance!$J$2:$J$10000,"C&B - BOQ",Balance!$F$2:$F$10000)
A27: Design | B27: BOQ | C27: =COUNTIF(Balance!$J$2:$J$10000,"Design - BOQ") | D27: =SUMIF(Balance!$J$2:$J$10000,"Design - BOQ",Balance!$F$2:$F$10000)
A28: Design | B28: Drawing | C28: =COUNTIF(Balance!$J$2:$J$10000,"Design - Drawing") | D28: =SUMIF(Balance!$J$2:$J$10000,"Design - Drawing",Balance!$F$2:$F$10000)
A33: Monthly Plan vs Achieved
A34: Month | B34: Plan / Budget | C34: Achieved | D34: Balance PTE
A35: 46113 | B35: =SUMIFS(Contracts!$I$2:$I$10000,Contracts!$G$2:$G$10000,">="&A35,Contracts!$G$2:$G$10000,"<="&EOMONTH(A35,0),Contracts!$H$2:$H$10000,1)+SUMIFS(Procurement!$F$2:$F$10000,Procurement!$E$2:$E$10000,">="&A35,Procurement!$E$2:$E$10000,"<="&EOMONTH(A35,0)) | C35: =SUMIFS(Contracts!$J$2:$J$10000,Contracts!$G$2:$G$10000,">="&A35,Contracts!$G$2:$G$10000,"<="&EOMONTH(A35,0),Contracts!$H$2:$H$10000,1)+SUMIFS(Procurement!$G$2:$G$10000,Procurement!$E$2:$E$10000,">="&A35,Procurement!$E$2:$E$10000,"<="&EOMONTH(A35,0)) | D35: =SUMIFS(Balance!$F$2:$F$10000,Balance!$E$2:$E$10000,">="&A35,Balance!$E$2:$E$10000,"<="&EOMONTH(A35,0))
A36: 46143 | B36: =SUMIFS(Contracts!$I$2:$I$10000,Contracts!$G$2:$G$10000,">="&A36,Contracts!$G$2:$G$10000,"<="&EOMONTH(A36,0),Contracts!$H$2:$H$10000,1)+SUMIFS(Procurement!$F$2:$F$10000,Procurement!$E$2:$E$10000,">="&A36,Procurement!$E$2:$E$10000,"<="&EOMONTH(A36,0)) | C36: =SUMIFS(Contracts!$J$2:$J$10000,Contracts!$G$2:$G$10000,">="&A36,Contracts!$G$2:$G$10000,"<="&EOMONTH(A36,0),Contracts!$H$2:$H$10000,1)+SUMIFS(Procurement!$G$2:$G$10000,Procurement!$E$2:$E$10000,">="&A36,Procurement!$E$2:$E$10000,"<="&EOMONTH(A36,0)) | D36: =SUMIFS(Balance!$F$2:$F$10000,Balance!$E$2:$E$10000,">="&A36,Balance!$E$2:$E$10000,"<="&EOMONTH(A36,0))
A37: 46174 | B37: =SUMIFS(Contracts!$I$2:$I$10000,Contracts!$G$2:$G$10000,">="&A37,Contracts!$G$2:$G$10000,"<="&EOMONTH(A37,0),Contracts!$H$2:$H$10000,1)+SUMIFS(Procurement!$F$2:$F$10000,Procurement!$E$2:$E$10000,">="&A37,Procurement!$E$2:$E$10000,"<="&EOMONTH(A37,0)) | C37: =SUMIFS(Contracts!$J$2:$J$10000,Contracts!$G$2:$G$10000,">="&A37,Contracts!$G$2:$G$10000,"<="&EOMONTH(A37,0),Contracts!$H$2:$H$10000,1)+SUMIFS(Procurement!$G$2:$G$10000,Procurement!$E$2:$E$10000,">="&A37,Procurement!$E$2:$E$10000,"<="&EOMONTH(A37,0)) | D37: =SUMIFS(Balance!$F$2:$F$10000,Balance!$E$2:$E$10000,">="&A37,Balance!$E$2:$E$10000,"<="&EOMONTH(A37,0))
A38: 46204 | B38: =SUMIFS(Contracts!$I$2:$I$10000,Contracts!$G$2:$G$10000,">="&A38,Contracts!$G$2:$G$10000,"<="&EOMONTH(A38,0),Contracts!$H$2:$H$10000,1)+SUMIFS(Procurement!$F$2:$F$10000,Procurement!$E$2:$E$10000,">="&A38,Procurement!$E$2:$E$10000,"<="&EOMONTH(A38,0)) | C38: =SUMIFS(Contracts!$J$2:$J$10000,Contracts!$G$2:$G$10000,">="&A38,Contracts!$G$2:$G$10000,"<="&EOMONTH(A38,0),Contracts!$H$2:$H$10000,1)+SUMIFS(Procurement!$G$2:$G$10000,Procurement!$E$2:$E$10000,">="&A38,Procurement!$E$2:$E$10000,"<="&EOMONTH(A38,0)) | D38: =SUMIFS(Balance!$F$2:$F$10000,Balance!$E$2:$E$10000,">="&A38,Balance!$E$2:$E$10000,"<="&EOMONTH(A38,0))
A39: 46235 | B39: =SUMIFS(Contracts!$I$2:$I$10000,Contracts!$G$2:$G$10000,">="&A39,Contracts!$G$2:$G$10000,"<="&EOMONTH(A39,0),Contracts!$H$2:$H$10000,1)+SUMIFS(Procurement!$F$2:$F$10000,Procurement!$E$2:$E$10000,">="&A39,Procurement!$E$2:$E$10000,"<="&EOMONTH(A39,0)) | C39: =SUMIFS(Contracts!$J$2:$J$10000,Contracts!$G$2:$G$10000,">="&A39,Contracts!$G$2:$G$10000,"<="&EOMONTH(A39,0),Contracts!$H$2:$H$10000,1)+SUMIFS(Procurement!$G$2:$G$10000,Procurement!$E$2:$E$10000,">="&A39,Procurement!$E$2:$E$10000,"<="&EOMONTH(A39,0)) | D39: =SUMIFS(Balance!$F$2:$F$10000,Balance!$E$2:$E$10000,">="&A39,Balance!$E$2:$E$10000,"<="&EOMONTH(A39,0))
A40: 46266 | B40: =SUMIFS(Contracts!$I$2:$I$10000,Contracts!$G$2:$G$10000,">="&A40,Contracts!$G$2:$G$10000,"<="&EOMONTH(A40,0),Contracts!$H$2:$H$10000,1)+SUMIFS(Procurement!$F$2:$F$10000,Procurement!$E$2:$E$10000,">="&A40,Procurement!$E$2:$E$10000,"<="&EOMONTH(A40,0)) | C40: =SUMIFS(Contracts!$J$2:$J$10000,Contracts!$G$2:$G$10000,">="&A40,Contracts!$G$2:$G$10000,"<="&EOMONTH(A40,0),Contracts!$H$2:$H$10000,1)+SUMIFS(Procurement!$G$2:$G$10000,Procurement!$E$2:$E$10000,">="&A40,Procurement!$E$2:$E$10000,"<="&EOMONTH(A40,0)) | D40: =SUMIFS(Balance!$F$2:$F$10000,Balance!$E$2:$E$10000,">="&A40,Balance!$E$2:$E$10000,"<="&EOMONTH(A40,0))
A41: 46296 | B41: =SUMIFS(Contracts!$I$2:$I$10000,Contracts!$G$2:$G$10000,">="&A41,Contracts!$G$2:$G$10000,"<="&EOMONTH(A41,0),Contracts!$H$2:$H$10000,1)+SUMIFS(Procurement!$F$2:$F$10000,Procurement!$E$2:$E$10000,">="&A41,Procurement!$E$2:$E$10000,"<="&EOMONTH(A41,0)) | C41: =SUMIFS(Contracts!$J$2:$J$10000,Contracts!$G$2:$G$10000,">="&A41,Contracts!$G$2:$G$10000,"<="&EOMONTH(A41,0),Contracts!$H$2:$H$10000,1)+SUMIFS(Procurement!$G$2:$G$10000,Procurement!$E$2:$E$10000,">="&A41,Procurement!$E$2:$E$10000,"<="&EOMONTH(A41,0)) | D41: =SUMIFS(Balance!$F$2:$F$10000,Balance!$E$2:$E$10000,">="&A41,Balance!$E$2:$E$10000,"<="&EOMONTH(A41,0))
A42: 46327 | B42: =SUMIFS(Contracts!$I$2:$I$10000,Contracts!$G$2:$G$10000,">="&A42,Contracts!$G$2:$G$10000,"<="&EOMONTH(A42,0),Contracts!$H$2:$H$10000,1)+SUMIFS(Procurement!$F$2:$F$10000,Procurement!$E$2:$E$10000,">="&A42,Procurement!$E$2:$E$10000,"<="&EOMONTH(A42,0)) | C42: =SUMIFS(Contracts!$J$2:$J$10000,Contracts!$G$2:$G$10000,">="&A42,Contracts!$G$2:$G$10000,"<="&EOMONTH(A42,0),Contracts!$H$2:$H$10000,1)+SUMIFS(Procurement!$G$2:$G$10000,Procurement!$E$2:$E$10000,">="&A42,Procurement!$E$2:$E$10000,"<="&EOMONTH(A42,0)) | D42: =SUMIFS(Balance!$F$2:$F$10000,Balance!$E$2:$E$10000,">="&A42,Balance!$E$2:$E$10000,"<="&EOMONTH(A42,0))
A43: 46357 | B43: =SUMIFS(Contracts!$I$2:$I$10000,Contracts!$G$2:$G$10000,">="&A43,Contracts!$G$2:$G$10000,"<="&EOMONTH(A43,0),Contracts!$H$2:$H$10000,1)+SUMIFS(Procurement!$F$2:$F$10000,Procurement!$E$2:$E$10000,">="&A43,Procurement!$E$2:$E$10000,"<="&EOMONTH(A43,0)) | C43: =SUMIFS(Contracts!$J$2:$J$10000,Contracts!$G$2:$G$10000,">="&A43,Contracts!$G$2:$G$10000,"<="&EOMONTH(A43,0),Contracts!$H$2:$H$10000,1)+SUMIFS(Procurement!$G$2:$G$10000,Procurement!$E$2:$E$10000,">="&A43,Procurement!$E$2:$E$10000,"<="&EOMONTH(A43,0)) | D43: =SUMIFS(Balance!$F$2:$F$10000,Balance!$E$2:$E$10000,">="&A43,Balance!$E$2:$E$10000,"<="&EOMONTH(A43,0))
A44: 46388 | B44: =SUMIFS(Contracts!$I$2:$I$10000,Contracts!$G$2:$G$10000,">="&A44,Contracts!$G$2:$G$10000,"<="&EOMONTH(A44,0),Contracts!$H$2:$H$10000,1)+SUMIFS(Procurement!$F$2:$F$10000,Procurement!$E$2:$E$10000,">="&A44,Procurement!$E$2:$E$10000,"<="&EOMONTH(A44,0)) | C44: =SUMIFS(Contracts!$J$2:$J$10000,Contracts!$G$2:$G$10000,">="&A44,Contracts!$G$2:$G$10000,"<="&EOMONTH(A44,0),Contracts!$H$2:$H$10000,1)+SUMIFS(Procurement!$G$2:$G$10000,Procurement!$E$2:$E$10000,">="&A44,Procurement!$E$2:$E$10000,"<="&EOMONTH(A44,0)) | D44: =SUMIFS(Balance!$F$2:$F$10000,Balance!$E$2:$E$10000,">="&A44,Balance!$E$2:$E$10000,"<="&EOMONTH(A44,0))
A45: 46419 | B45: =SUMIFS(Contracts!$I$2:$I$10000,Contracts!$G$2:$G$10000,">="&A45,Contracts!$G$2:$G$10000,"<="&EOMONTH(A45,0),Contracts!$H$2:$H$10000,1)+SUMIFS(Procurement!$F$2:$F$10000,Procurement!$E$2:$E$10000,">="&A45,Procurement!$E$2:$E$10000,"<="&EOMONTH(A45,0)) | C45: =SUMIFS(Contracts!$J$2:$J$10000,Contracts!$G$2:$G$10000,">="&A45,Contracts!$G$2:$G$10000,"<="&EOMONTH(A45,0),Contracts!$H$2:$H$10000,1)+SUMIFS(Procurement!$G$2:$G$10000,Procurement!$E$2:$E$10000,">="&A45,Procurement!$E$2:$E$10000,"<="&EOMONTH(A45,0)) | D45: =SUMIFS(Balance!$F$2:$F$10000,Balance!$E$2:$E$10000,">="&A45,Balance!$E$2:$E$10000,"<="&EOMONTH(A45,0))
A46: 46447 | B46: =SUMIFS(Contracts!$I$2:$I$10000,Contracts!$G$2:$G$10000,">="&A46,Contracts!$G$2:$G$10000,"<="&EOMONTH(A46,0),Contracts!$H$2:$H$10000,1)+SUMIFS(Procurement!$F$2:$F$10000,Procurement!$E$2:$E$10000,">="&A46,Procurement!$E$2:$E$10000,"<="&EOMONTH(A46,0)) | C46: =SUMIFS(Contracts!$J$2:$J$10000,Contracts!$G$2:$G$10000,">="&A46,Contracts!$G$2:$G$10000,"<="&EOMONTH(A46,0),Contracts!$H$2:$H$10000,1)+SUMIFS(Procurement!$G$2:$G$10000,Procurement!$E$2:$E$10000,">="&A46,Procurement!$E$2:$E$10000,"<="&EOMONTH(A46,0)) | D46: =SUMIFS(Balance!$F$2:$F$10000,Balance!$E$2:$E$10000,">="&A46,Balance!$E$2:$E$10000,"<="&EOMONTH(A46,0))
A49: Calculation basis
A50: Plan = unique awarded-IOM budget + unique procurement-IOM budget + recorded PTE for balance work scheduled in the selected period.
A51: Achieved = unique contract award value + unique procurement award value. Multi-vendor procurement IOMs are counted once.
A52: Update values in Contracts, Procurement or Balance tabs. Blank values are excluded and begin contributing automatically when filled.

Sheet Contracts
A1: IOM Version | B1: Project | C1: Package | D1: Awarded Vendor | E1: TES / Non-TES | F1: Requisition Date | G1: Award Date | H1: Unique Flag | I1: Budget (₹ Cr) | J1: Unique Award (₹ Cr)
A2: IOMC20260425052514 | B2: Godrej Joka | C2: Civil - General | D2: Ada Metcon | E2: TES | F2: 46135 | G2: 46138 | H2: 1 | I2: 0.387 | J2: 0.322
A3: IOMC20260425063240 | B3: Godrej Joka | C3: Miscellaneous / other | D3: Indicative Consultant India | E3: Non-TES | F3: 46135 | G3: 46138 | H3: 1 | I3: 0.018 | J3: 0.01374
A4: IOMC20260512064130 | B4: Godrej Joka | C4: Finishing - Painting | D4: Maa Tara Enterprise | E4: TES | F4: 46128 | G4: 46155 | H4: 1 | I4: 1.35 | J4: 2.228
A5: IOMC20260512064130 | B5: Godrej Joka | C5: Finishing - Painting | D5: MOZAMMEL SEKH | E5: TES | F5: 46128 | G5: 46155 | H5: 0 | I5: 1.35 | J5: 0
A6: IOMC20260520065412 | B6: Godrej Joka | C6: Miscellaneous / other | D6: JRS CONSTRUCTION | E6: Non-TES | F6: 46129 | G6: 46163 | H6: 1 | I6: 0.213 | J6: 0.196
A7: IOMC20260529050740 | B7: Godrej Joka | C7: Miscellaneous | D7: VISHAL JAISWAL | E7: Non-TES | F7: 46169 | G7: 46172 | H7: 1 | I7: 0.2175 | J7: 0.2175
A8: IOMC20260529051614 | B8: Godrej Joka | C8: Miscellaneous | D8: KISHAN JAISWAL | E8: Non-TES | F8: 46169 | G8: 46172 | H8: 1 | I8: 0.2175 | J8: 0.2175
A9: IOMC20260603012523 | B9: Godrej Joka | C9: Miscellaneous | D9: VISHAL JAISWAL | E9: Non-TES | F9: 46169 | G9: 46177 | H9: 1 | I9: 0.23925 | J9: 0.23925
A10: IOMC20260603013034 | B10: Godrej Joka | C10: Miscellaneous | D10: KISHAN JAISWAL | E10: Non-TES | F10: 46169 | G10: 46177 | H10: 1 | I10: 0.23925 | J10: 0.23925
A11: IOMC20260613063044 | B11: Godrej Joka | C11: Civil - Water Proofing and Expansion Joints | D11: PURVYAKRUTI SALES & SERVICES PRIVATE LIMITED | E11: TES | F11: 46169 | G11: 46187 | H11: 1 | I11: 1.488 | J11: 3.569
A12: IOMC20260613063044 | B12: Godrej Joka | C12: Civil - Water Proofing and Expansion Joints | D12: JSS ENGINEERING PRIVATE LIMITED | E12: TES | F12: 46169 | G12: 46187 | H12: 0 | I12: 2.232 | J12: 0
A13: IOMC20260624011203 | B13: Godrej Joka | C13: Miscellaneous | D13: RABI CONSTRUCTION | E13: Non-TES | F13: 46193 | G13: 46198 | H13: 1 | I13: 0.0058 | J13: 0.0045
... A66: IOMC20260814184540 | B66: B L saha | C66: Miscellaneous | D66: ZOYA ENGINEERING & CONSTRUCTION COMPANY | E66: Non-TES | F66: 46246 | G66: 46249 | H66: 1 | I66: 0.0193 | J66: 0.0179
A67: IOMC20260820145119 | B67: B L saha | C67: Miscellaneous | D67: G S Automation | F67: 46238 | G67: 46255 | H67: 1 | I67: 0.1152 | J67: 0.1104
A68: IOMC20260827161019 | B68: B L saha | C68: MEP - Lifts | D68: Schindler India Pvt. Ltd. | F68: 46135 | G68: 46262 | H68: 1 | I68: 7.74 | J68: 6.91
A69: IOMC20260827201049 | B69: B L saha | C69: MEP - Plumbing | D69: SANITECH INFRASTRUCTURES PVT LTD | F69: 46241 | G69: 46262 | H69: 1 | I69: 0.0467 | J69: 0.0366
A70: IOMC20260331125218 | B70: Godrej Ushti 1 | C70: Miscellaneous | D70: P.T.Enterprise | E70: Non-TES | F70: 46099 | G70: 46113 | H70: 1 | I70: 0.0044 | J70: 0.0044
A71: IOMC20260420111543 | B71: Godrej Ushti 1 | C71: Miscellaneous / other | D71: Loyalie It Solutions Pvt Ltd | E71: Non-TES | F71: 46132 | G71: 46133 | H71: 1 | I71: 0.0253 | J71: 0.0253
A72: IOMC20260422104844 | B72: Godrej Ushti 1 | C72: MOSA infrastructure work | D72: GREEN VIEW | E72: Non-TES | F72: 46126 | G72: 46135 | H72: 1 | I72: 0.013 | J72: 0.0124
A73: IOMC20260504065517 | B73: Godrej Ushti 1 | C73: Civil - General | D73: M&M Foundation | E73: TES | F73: 46108 | G73: 46147 | H73: 1 | I73: 1.6445 | J73: 1.6002
A74: IOMC20260508120852 | B74: Godrej Ushti 1 | C74: Civil - General | D74: SUDHIR KUMAR DHIRAJ KUMAR | E74: TES | F74: 46143 | G74: 46151 | H74: 1 | I74: 0.2999 | J74: 0.2886
A75: IOMC20260519103610 | B75: Godrej Ushti 1 | C75: MEP - Electrical | D75: B.R.CONSTRUCTION | E75: TES | F75: 46100 | G75: 46162 | H75: 1 | I75: 0.249 | J75: 0.2311
A76: IOMC20260527035005 | B76: Godrej Ushti 1 | C76: Civil - General | D76: SGK INFRA ARCHITECTURE CO | E76: TES | F76: 46143 | G76: 46170 | H76: 1 | I76: 0.7136 | J76: 0.6759
A77: IOMC20260609060953 | B77: Godrej Ushti 1 | C77: Supply of material | D77: SOOR NEOGI COOMAR & CO. PVT. LTD. | E77: Non-TES | F77: 46177 | G77: 46183 | H77: 1 | I77: 0.1381 | J77: 0.1381
A78: IOMC20260609080222 | B78: Godrej Ushti 1 | C78: Supply of material | D78: PAVE INDIA ENTERPRISE | E78: Non-TES | F78: 46182 | G78: 46183 | H78: 1 | I78: 0.0644 | J78: 0.0644
A79: IOMC20260618023626 | B79: Godrej Ushti 1 | C79: Housekeeping, site office, temporary office | D79: Sudhir Kumar Dhiraj Kumar | E79: Non-TES | F79: 46183 | G79: 46192 | H79: 1 | I79: 0.0825 | J79: 0.0781
A80: IOMC20260618041029 | B80: Godrej Ushti 1 | C80: Infrastructure - Sinages | D80: A K Enterprise | E80: TES | F80: 46162 | G80: 46192 | H80: 1 | I80: 0.2801 | J80: 0.2606
A81: IOMC20260629040050 | B81: Godrej Ushti 1 | C81: MEP - Electrical | D81: RSM PROJECTS & ENGINEERS PRIVATE LIMITED | E81: TES | F81: 46173 | G81: 46203 | H81: 1 | I81: 0.2239 | J81: 0.1072
... A92: IOMC20260816115058 | B92: Godrej Ushti 1 | C92: Infrastructure - Landscaping/Softscape | D92: ROYAL MICRO IRRIGATION SYSTEMS | E92: Non-TES | F92: 46246 | G92: 46251 | H92: 0 | I92: 0.44 | J92: 0
A93: IOMC20260902145936 | B93: Godrej Ushti 1 | C93: Civil - General | D93: ZOYA ENGINEERING & CONSTRUCTION COMPANY | F93: 46261 | G93: 46268 | H93: 1 | I93: 0.2302 | J93: 0.2244
A94: IOMC20260409041716 | B94: Raipur Plotted 1 | C94: MEP - STP / WTP | D94: PTC WATERTECH LLP | F94: 46115 | G94: 46122 | H94: 1 | I94: 0.7711 | J94: 0.6951
A95: IOMC20260416064433 | B95: Raipur Plotted 1 | C95: Miscellaneous | D95: PS Enterprises | F95: 46124 | G95: 46129 | H95: 1 | I95: 0.0069 | J95: 0.0067
A96: IOMC20260416072113 | B96: Raipur Plotted 1 | C96: Miscellaneous | D96: SMS INTEGRATED FACILITY SERVICES PRIVATE LIMITED | F96: 46124 | G96: 46129 | H96: 1 | I96: 0.0111 | J96: 0.0111
A97: IOMC20260423061721 | B97: Raipur Plotted 1 | C97: MEP - Electrical | D97: Acharya Electrical | F97: 46114 | G97: 46136 | H97: 1 | I97: 3.8238 | J97: 3.6505
A98: IOMC20260424070952 | B98: Raipur Plotted 1 | C98: Miscellaneous / other | D98: LOYALIE-IT SOLUTIONS PRIVATE LIMITED | F98: 46132 | G98: 46137 | H98: 1 | I98: 0.0102 | J98: 0.0102
A99: IOMC20260515120423 | B99: Raipur Plotted 1 | C99: Finishing - Painting | D99: Khan Enterprise | F99: 46151 | G99: 46158 | H99: 1 | I99: 0.0428 | J99: 0.0207
A100: IOMC20260525034756 | B100: Raipur Plotted 1 | C100: Miscellaneous | D100: OMEGA TEST HOUSE PRIVATE LIMITED | F100: 46164 | G100: 46168 | H100: 1 | I100: 0.0057 | J100: 0.0055
A101: IOMC20260603062823 | B101: Raipur Plotted 1 | C101: Civil - Core & Shell | D101: VINOD KUMAR JAIN | F101: 45781 | G101: 46177 | H101: 1 | I101: 0.8072 | J101: 0.7857
A102: IOMC20260604064423 | B102: Raipur Plotted 1 | C102: Civil - Core & Shell | D102: VINOD KUMAR JAIN | F102: 46146 | G102: 46178 | H102: 1 | I102: 0.3928 | J102: 0.3794
A103: IOMC20260607123916 | B103: Raipur Plotted 1 | C103: Civil - Core & Shell | D103: VINOD KUMAR JAIN | F103: 46160 | G103: 46178 | H103: 1 | I103: 0.3348 | J103: 0.3248
A104: IOMC20260611120616 | B104: Raipur Plotted 1 | C104: Miscellaneous | D104: NITA FIRE SAFETY SOLUTIONS | F104: 46183 | G104: 46185 | H104: 1 | I104: 0.0059 | J104: 0.0059
... A113: IOMC20260516112107 | B113: Godrej Nonadanga | C113: Civil - General | D113: SUDHIR KUMAR DHIRAJ KUMAR | F113: 46146 | G113: 46159 | H113: 1 | I113: 0.4251 | J113: 0.3571

Sheet Procurement
A1: IOM Version | B1: Project | C1: Package | D1: TES / Non-TES | E1: Award Date | F1: Budget (₹ Cr) | G1: Award Value (₹ Cr) | H1: Awarded Count
A2: IOMP20260330110946 | B2: Godrej Joka | C2: Miscellaneous / other works | D2: Non-TES | E2: 46111 | F2: 0.0147 | G2: 0.0147 | H2: 1
A3: IOMP20260402084753 | B3: Godrej Joka | C3: Civil - RMC | D3: TES | E3: 46114 | F3: 1.8 | G3: 1.7726 | H3: 1
A4: IOMP20260407041146 | B4: Godrej Joka | C4: Civil - Steel Rebar | D4: TES | E4: 46119 | F4: 1.041 | G4: 1.0379 | H4: 1
A5: IOMP20260408112501 | B5: Godrej Joka | C5: Civil - RMC | D5: TES | E5: 46120 | F5: 1.1658 | G5: 1.094 | H5: 1
A6: IOMP20260409085044 | B6: Godrej Joka | C6: Miscellaneous / other works | D6: Non-TES | E6: 46121 | F6: 0.00766 | G6: 0.00766 | H6: 1
A7: IOMP20260425035921 | B7: Godrej Joka | C7: Miscellaneous / other works | D7: Non-TES | E7: 46137 | F7: 0.0144 | G7: 0.0144 | H7: 1
A8: IOMP20260425041300 | B8: Godrej Joka | C8: Miscellaneous / other works | D8: Non-TES | E8: 46137 | F8: 0.0644 | G8: 0.0644 | H8: 1
A9: IOMP20260427103519 | B9: Godrej Joka | C9: Civil - Steel Rebar | D9: TES | E9: 46139 | F9: 0.7194 | G9: 0.6346 | H9: 1
A10: IOMP20260504043440 | B10: Godrej Joka | C10: Civil - RMC | D10: TES | E10: 46146 | F10: 0.9609 | G10: 0.9321 | H10: 1
A11: IOMP20260511031924 | B11: Godrej Joka | C11: Civil - Aluminium Formwork | E11: 46153 | F11: 13.63 | G11: 13.41 | H11: 1
A12: IOMP20260515104639 | B12: Godrej Joka | C12: Civil - Steel Rebar | D12: TES | E12: 46157 | F12: 0.396 | G12: 0.3736 | H12: 1
A13: IOMP20260521062624 | B13: Godrej Joka | C13: Civil - RMC | D13: TES | E13: 46163 | F13: 0.1192 | G13: 0.1175 | H13: 1
A14: IOMP20260522100422 | B14: Godrej Joka | C14: Civil - RMC | D14: TES | E14: 46164 | F14: 0.972 | G14: 0.9532 | H14: 1
A15: IOMP20260527110324 | B15: Godrej Joka | C15: Civil - Steel Rebar | D15: TES | E15: 46169 | F15: 0.198 | G15: 0.1836 | H15: 1
A16: IOMP20260608070120 | B16: Godrej Joka | C16: Civil - RMC | D16: TES | E16: 46181 | F16: 1.4771 | G16: 1.4134 | H16: 1
A17: IOMP20260618122433 | B17: Godrej Joka | C17: Miscellaneous / other works | E17: 46191 | F17: 0.00728 | G17: 0.00728 | H17: 1
A18: IOMP20260709122844 | B18: Godrej Joka | C18: Civil - Steel Rebar | D18: TES | E18: 46212 | F18: 1.3514 | G18: 1.1674 | H18: 1
A19: IOMP20260718122004 | B19: Godrej Joka | C19: Civil - Cement | E19: 46221 | F19: 0.0229 | G19: 0.0229 | H19: 1
A20: IOMP20260718123408 | B20: Godrej Joka | C20: Miscellaneous / other works | E20: 46221 | F20: 0.0253 | G20: 0.0253 | H20: 1
A21: IOMP20260718125148 | B21: Godrej Joka | C21: Miscellaneous / other works | E21: 46221 | F21: 0.041 | G21: 0.041 | H21: 1
A22: IOMP20260723193610 | B22: Godrej Joka | C22: Finishing - Tiles | E22: 46226 | F22: 0.1062 | G22: 0.1032 | H22: 1
A23: IOMP20260729173346 | B23: Godrej Joka | C23: MEP - Plumbing and Fire fighting equipments and fittings | E23: 46232 | F23: 0.65 | G23: 0.538 | H23: 1
A24: IOMP20260730121059 | B24: Godrej Joka | C24: Finishing - Tiles | E24: 46233 | F24: 0.1844 | G24: 0.1727 | H24: 1
A25: IOMP20260730205912 | B25: Godrej Joka | C25: Miscellaneous / other works | E25: 46233 | F25: 0.00183 | G25: 0.00183 | H25: 1
A26: IOMP20260730211650 | B26: Godrej Joka | C26: Civil - RMC | E26: 46233 | F26: 1.647 | G26: 1.583 | H26: 1
A27: IOMP20260731201247 | B27: Godrej Joka | C27: MEP - Electrical equipment and fitting | E27: 46234 | F27: 0.0394 | G27: 0.03773 | H27: 1
A28: IOMP20260816164958 | B28: Godrej Joka | C28: Miscellaneous / other works | E28: 46250 | F28: 0.0073 | G28: 0.0073 | H28: 1
A29: IOMP20260816170023 | B29: Godrej Joka | C29: Miscellaneous / other works | E29: 46250 | F29: 0.1368 | G29: 0.0895 | H29: 1
A30: IOMP20260819195811 | B30: Godrej Joka | C30: Civil - Steel Rebar | E30: 46253 | F30: 2.1594 | G30: 1.8844 | H30: 1
... A60: IOMP20260808121155 | B60: Godrej Ushti 1 | C60: Civil - RMC | E60: 46242 | F60: 0.0451 | G60: 0.0449 | H60: 1

Sheet Balance
A1: Project | B1: Contract Award Package | C1: Revised Plan Date | D1: Actual/CBE Award Date | E1: Schedule Date | F1: PTE Value (₹ Cr) | G1: BOQ Status | H1: Drawing Status | I1: Currently With | J1: Dependency
A2: Godrej Blue | B2: Windows | C2: 46256 | D2: 46276 | E2: 46276 | G2: Provided | H2: Provided | I2: C&P
A3: Godrej Blue | B3: Glass Railing | C3: 46295 | D3: 46295 | E3: 46295 | G3: Provided | H3: Provided | I3: C&P
A4: Godrej Blue | B4: Sub station -Core &Shell | C4: 46272 | D4: 46272 | E4: 46272 | F4: 1.34 | G4: Provided | H4: Provided | I4: C&P
A5: Godrej Blue | B5: CP Fittings and Sanitary Fixtures including Kitchen sink | C5: 46275 | D5: 46276 | E5: 46276 | F5: 6.28 | G5: Provided | H5: Provided | I5: C&P
A6: Godrej Blue | B6: External Painting | C6: 46276 | D6: 46286 | E6: 46286 | F6: 4.5 | G6: Provided | H6: Not provided | I6: Design | J6: Design - Drawing
A7: Godrej Blue | B7: Fire Door | C7: 46280 | D7: 46280 | E7: 46280 | F7: 1.67 | G7: Provided | H7: Provided | I7: C&P
A8: Godrej Blue | B8: Internal Electrical | C8: 46276 | D8: 46276 | E8: 46276 | F8: 0.107 | G8: Provided | H8: Provided | I8: C&P
A9: Godrej Blue | B9: Light Fittings | C9: 46355 | D9: 46310 | E9: 46310 | F9: 5 | G9: Not provided | H9: Provided | I9: C&B | J9: C&B - BOQ
A10: Godrej Blue | B10: Louvers for Tower Area | C10: 46296 | D10: 46296 | E10: 46296 | F10: 0.4 | G10: Not provided | H10: Provided | I10: C&B | J10: C&B - BOQ
A11: Godrej Blue | B11: Solar | C11: 46369 | D11: 46369 | E11: 46369 | F11: 1.7 | G11: Provided | H11: Provided | I11: C&P
A12: Godrej Blue | B12: DG | C12: 46338 | D12: 46338 | E12: 46338 | G12: Provided | H12: Provided | I12: C&P
A13: Godrej Blue | B13: Play Amenities( Cricket ground, Basket Ball ground, jogging etc.) | C13: 46510 | D13: 46510 | E13: 46510 | F13: 0.65 | G13: Not provided | H13: Provided | I13: C&B | J13: C&B - BOQ
A14: Godrej Blue | B14: Internal Electrical - Panels | C14: 46307 | E14: 46307 | G14: Provided | H14: Provided | I14: C&P
A15: Godrej Blue | B15: Fire Fighting - Pumps | C15: 46352 | D15: 46352 | E15: 46352 | F15: 0.25 | G15: Provided | H15: Provided | I15: C&P
A16: Godrej Blue | B16: Fire Fighting - Panels | C16: 46352 | D16: 46352 | E16: 46352 | F16: 0.067 | G16: Provided | H16: Provided | I16: C&P
A17: Godrej Blue | B17: Expansion Joint | C17: 46292 | D17: 46285 | E17: 46285 | F17: 0.46 | G17: Provided | H17: Provided | I17: C&P
A18: Godrej Blue | B18: External Plumbing - Pumps & Panels | C18: 46367 | D18: 46367 | E18: 46367 | F18: 0.7 | G18: Provided | H18: Provided | I18: C&P
A19: Godrej Blue | B19: External Electrical - Panels | C19: 46367 | D19: 46367 | E19: 46367 | G19: Provided | H19: Provided | I19: C&P
A20: Godrej Blue | B20: Hardscape | C20: 46299 | D20: 46299 | E20: 46299 | F20: 2.14 | G20: Not provided | H20: Provided | I20: C&B | J20: C&B - BOQ
A21: Godrej Blue | B21: Softscape-shurbs | C21: 46299 | D21: 46299 | E21: 46299 | F21: 2.5 | G21: Not provided | H21: Provided | I21: C&B | J21: C&B - BOQ
A22: Godrej Blue | B22: Plantation | C22: 46288 | D22: 46288 | E22: 46288 | F22: 1.8 | G22: Provided | H22: Provided | I22: C&P
A23: Godrej Blue | B23: Road | C23: 46308 | D23: 46308 | E23: 46308 | F23: 0.35 | G23: Not provided | H23: Provided | I23: C&B | J23: C&B - BOQ
A24: Godrej Blue | B24: FAPA, CCTV | C24: 46308 | D24: 46308 | E24: 46308 | F24: 3.25 | G24: Provided | H24: Provided | I24: C&P
A25: Godrej Blue | B25: Security, Boom Barriers | C25: 46308 | D25: 46308 | E25: 46308 | F25: 0.75 | G25: Not provided | H25: Provided | I25: C&B | J25: C&B - BOQ
A26: Godrej Blue | B26: External Illumination | C26: 46308 | D26: 46308 | E26: 46308 | F26: 0.85 | G26: Not provided | H26: Not provided | I26: Design | J26: Design - BOQ
A27: Godrej Blue | B27: Club House Core & Shell | C27: 46357 | D27: 46357 | E27: 46357 | F27: 3.07 | G27: Provided | H27: Provided | I27: C&P
A28: Godrej Blue | B28: Louver for Non Tower | C28: 46419 | D28: 46419 | E28: 46419 | F28: 1.5 | G28: Not provided | H28: Not provided | I28: Design | J28: Design - BOQ
A29: Godrej Blue | B29: Timber Structure work for Tree House, Board Walk & Viewing Platform | C29: 46463 | D29: 46463 | E29: 46463 | F29: 1.5 | G29: Not provided | H29: Not provided | I29: Design | J29: Design - BOQ
A30: Godrej Blue | B30: Club House Interiors | C30: 46469 | D30: 46469 | E30: 46469 | F30: 7.22 | G30: Not provided | H30: Provided | I30: C&B | J30: C&B - BOQ
A31: Godrej Se7en, Phase 2A | B31: Panels except High Side | C31: 46245 | D31: 46359 | E31: 46359 | F31: 0.5 | G31: Not provided | H31: Provided | I31: C&B | J31: C&B - BOQ
A32: Godrej Se7en, Phase 2A | B32: DG | C32: 46220 | D32: 46310 | E32: 46310 | G32: Provided | H32: Provided | I32: C&P
A33: Godrej Se7en, Phase 2A | B33: External Firefighting | C33: 46216 | D33: 46271 | E33: 46271 | G33: Provided | H33: Provided | I33: C&P
A34: Godrej Se7en, Phase 2A | B34: Swimming Pool | C34: 46308 | D34: 46197 | E34: 46197 | G34: Provided | H34: Provided | I34: C&P
A35: Godrej Se7en, Phase 2A | B35: Road | C35: 46214 | D35: 46347 | E35: 46347 | F35: 1 | G35: Not provided | H35: Provided | I35: C&B | J35: C&B - BOQ
A36: Godrej Se7en, Phase 2A | B36: Hard Scape Work | C36: 46201 | D36: 46308 | E36: 46308 | G36: Provided | H36: Provided | I36: C&P
A37: Godrej Se7en, Phase 2A | B37: Landscape Work | C37: 46293 | D37: 46308 | E37: 46308 | G37: Provided | H37: Provided | I37: C&P
A38: Godrej Se7en, Phase 2A | B38: Club House Finishing & Interiors incl MEP & HVAC | C38: 46286 | D38: 46240 | E38: 46240 | G38: Provided | H38: Provided | I38: C&P
A39: Godrej Se7en, Phase 2A | B39: FTTH & CCTV, Video Door Phone, Access Control | C39: 46137 | D39: 46340 | E39: 46340 | F39: 0.5 | G39: Not provided | H39: Not provided | I39: Design | J39: Design - BOQ
A40: Godrej Se7en, Phase 2A | B40: SITC Sports flooring | C40: 46280 | D40: 46302 | E40: 46302 | G40: Not provided | H40: Provided | I40: C&B | J40: C&B - BOQ
A41: Godrej Se7en, Phase 2A | B41: Soft Furnishing Club House | C41: 46280 | D41: 46297 | E41: 46297 | G41: Not provided | H41: Provided | I41: C&B | J41: C&B - BOQ
A42: Godrej Se7en, Phase 2A | B42: Gym Equipment & Play Equipment in Club House | C42: 46280 | D42: 46238 | E42: 46238 | G42: Provided | H42: Provided | I42: C&P
A43: Godrej Se7en, Phase 2A | B43: External Illumination | C43: 46275 | D43: 46305 | E43: 46305 | F43: 0.25 | G43: Not provided | H43: Provided | I43: C&B | J43: C&B - BOQ
A44: Godrej Se7en, Phase 2A | B44: External Louver for Non Tower | C44: 46306 | D44: 46265 | E44: 46265 | G44: Provided | H44: Provided | I44: C&P
A45: Godrej Se7en, Phase 2A | B45: Sculptures | C45: 46311 | D45: 46341 | E45: 46341 | F45: 0.2 | G45: Not provided | H45: Not provided | I45: Design | J45: Design - BOQ
A46: Godrej Se7en, Phase 2B | B46: Fire Fighting - Panels | C46: 46377 | D46: 46216 | E46: 46216 | G46: Provided | H46: Provided | I46: C&P
A47: Godrej Se7en, Phase 2B | B47: External Plumbing - Panels | C47: 46299 | D47: 46234 | E47: 46234 | G47: Provided | H47: Provided | I47: C&P
A48: Godrej Se7en, Phase 2B | B48: External Electrical -HT Panel | C48: 46268 | D48: 46380 | E48: 46380 | F48: 1 | G48: Not provided | H48: Not provided | I48: Design | J48: Design - BOQ
A49: Godrej Se7en, Phase 2B | B49: External Electrical - Panels except High Side | C49: 46239 | D49: 46234 | E49: 46234 | G49: Not provided | H49: Provided | I49: C&B | J49: C&B - BOQ
A50: Godrej Se7en, Phase 2B | B50: Solar | C50: 46261 | D50: 46267 | E50: 46267 | F50: 0.13 | G50: Provided | H50: Provided | I50: C&P
A51: Godrej Se7en, Phase 2B | B51: DG | C51: 46400 | D51: 46204 | E51: 46204 | G51: Provided | H51: Provided | I51: C&P
A52: Godrej Se7en, Phase 2B | B52: Road | C52: 46307 | D52: 46323 | E52: 46323 | F52: 1 | G52: Provided | H52: Provided | I52: C&P
A53: Godrej Se7en, Phase 2B | B53: Hardscape | C53: 46299 | D53: 46299 | E53: 46299 | G53: Provided | H53: Provided | I53: C&P
A54: Godrej Se7en, Phase 2B | B54: Softscape | C54: 46299 | D54: 46299 | E54: 46299 | G54: Provided | H54: Provided | I54: C&P
A55: Godrej Se7en, Phase 2B | B55: Club House Interiors | C55: 46335 | D55: 46335 | E55: 46335 | F55: 2.4 | G55: Provided | H55: Provided | I55: C&P
A56: Godrej Se7en, Phase 2B | B56: FAPA and CCTV and FTTH, Security, Boom Barriers | C56: 46341 | D56: 46277 | E56: 46277 | G56: Provided | H56: Provided | I56: C&P
A57: Godrej Se7en, Phase 2B | B57: Play Amenities | C57: 46350 | D57: 46350 | E57: 46350 | F57: 0.25 | G57: Provided | H57: Provided | I57: C&P
A58: Godrej Se7en, Phase 2B | B58: Children's Play Equipments | C58: 46350 | D58: 46350 | E58: 46350 | F58: 0.15 | G58: Provided | H58: Provided | I58: C&P
A59: Godrej Se7en, Phase 2B | B59: Gym Equipments | C59: 46350 | D59: 46350 | E59: 46350 | F59: 0.07 | G59: Provided | H59: Provided | I59: C&P
A60: Godrej Se7en, Elevate | B60: Internal Plumbing | C60: 46207 | D60: 46280 | E60: 46280 | G60: Provided | H60: Provided | I60: C&P
A61: Godrej Se7en, Elevate | B61: CP Fittings and Sanitary Fixtures | C61: 46265 | D61: 46318 | E61: 46318 | G61: Provided | H61: Provided | I61: C&P
A62: Godrej Se7en, Elevate | B62: Fire Fighting | C62: 46222 | D62: 46268 | E62: 46268 | F62: 2.9 | G62: Provided | H62: Provided | I62: C&P
A63: Godrej Se7en, Elevate | B63: Fire Fighting - Pumps | C63: 46355 | D63: 46268 | E63: 46268 | F63: 0.3 | G63: Provided | H63: Provided | I63: C&P
A64: Godrej Se7en, Elevate | B64: Fire Fighting - Panels | C64: 46415 | D64: 46268 | E64: 46268 | F64: 0.15 | G64: Provided | H64: Provided | I64: C&P
A65: Godrej Se7en, Elevate | B65: DB, MCB, RCCB | C65: 46526 | D65: 46250 | E65: 46250 | G65: Provided | H65: Provided | I65: C&P
A66: Godrej Se7en, Elevate | B66: Internal Electrical - Panels | C66: 46618 | D66: 46280 | E66: 46280 | G66: Provided | H66: Provided | I66: C&P
A67: Godrej Se7en, Elevate | B67: Windows, Louvers, FAÇADE and Fins | C67: 46265 | D67: 46338 | E67: 46338 | F67: 4.5 | G67: Provided | H67: Provided | I67: C&P
A68: Godrej Se7en, Elevate | B68: External Painting | C68: 46371 | D68: 46371 | E68: 46371 | F68: 2.4 | G68: Not provided | H68: Not provided | I68: Design | J68: Design - BOQ
A69: Godrej Se7en, Elevate | B69: Lift | C69: 46245 | D69: 46245 | E69: 46245 | G69: Provided | H69: Provided | I69: C&P
A70: Godrej Se7en, Elevate | B70: External Plumbing | C70: 46387 | D70: 46280 | E70: 46280 | G70: Provided | H70: Provided | I70: C&P
A71: Godrej Se7en, Elevate | B71: External Plumbing - Pumps | C71: 46371 | D71: 46280 | E71: 46280 | G71: Provided | H71: Provided | I71: C&P
A72: Godrej Se7en, Elevate | B72: External Plumbing - Panels | C72: 46431 | D72: 46280 | E72: 46280 | G72: Provided | H72: Provided | I72: C&P
A73: Godrej Se7en, Elevate | B73: External Electrical | C73: 46387 | D73: 46280 | E73: 46280 | F73: 1.5 | G73: Provided | H73: Provided | I73: C&P
A74: Godrej Se7en, Elevate | B74: External Electrical - Panels | C74: 46371 | D74: 46280 | E74: 46280 | F74: 1 | G74: Provided | H74: Provided | I74: C&P
A75: Godrej Se7en, Elevate | B75: Solar | C75: 46338 | D75: 46338 | E75: 46338 | F75: 0.12 | G75: Provided | H75: Provided | I75: C&P
A76: Godrej Se7en, Elevate | B76: DG | C76: 46558 | D76: 46280 | E76: 46280 | F76: 1.4 | G76: Not provided | H76: Provided | I76: C&B | J76: C&B - BOQ
A77: Godrej Se7en, Elevate | B77: Road | C77: 46446 | D77: 46446 | E77: 46446 | F77: 1.5 | G77: Not provided | H77: Not provided | I77: Design | J77: Design - BOQ
A78: Godrej Se7en, Elevate | B78: Hardscape | C78: 46451 | D78: 46451 | E78: 46451 | F78: 0.7 | G78: Not provided | H78: Not provided | I78: Design | J78: Design - BOQ
A79: Godrej Se7en, Elevate | B79: Softscape | C79: 46451 | D79: 46451 | E79: 46451 | F79: 0.4 | G79: Not provided | H79: Not provided | I79: Design | J79: Design - BOQ
A80: Godrej Se7en, Elevate | B80: Club House Interiors | C80: 46436 | D80: 46436 | E80: 46436 | F80: 2 | G80: Not provided | H80: Not provided | I80: Design | J80: Design - BOQ
A81: Godrej Se7en, Elevate | B81: HVAC Package | C81: 46436 | D81: 46297 | E81: 46297 | G81: Provided | H81: Provided | I81: C&P
A82: Godrej Se7en, Elevate | B82: FAPA and CCTV and FTTH, Security, Boom Barriers | C82: 46436 | D82: 46282 | E82: 46282 | G82: Provided | H82: Provided | I82: C&P
A83: Godrej Se7en, Elevate | B83: Play Amenities | C83: 46436 | D83: 46436 | E83: 46436 | F83: 0.25 | G83: Not provided | H83: Not provided | I83: Design | J83: Design - BOQ
A84: Godrej Se7en, Elevate | B84: Children's Play Equipments | C84: 46436 | D84: 46436 | E84: 46436 | F84: 0.15 | G84: Not provided | H84: Not provided | I84: Design | J84: Design - BOQ
A85: Godrej Se7en, Elevate | B85: Gym Equipments | C85: 46436 | D85: 46436 | E85: 46436 | F85: 0.07 | G85: Not provided | H85: Not provided | I85: Design | J85: Design - BOQ
A86: Plotted Development at Usthi | B86: New Culvert Construction | C86: 46203 | D86: 46203 | E86: 46203 | G86: provided | H86: Provided | I86: C&P
A87: Plotted Development at Usthi | B87: Irrigation Work | C87: 46226 | D87: 46226 | E87: 46226 | G87: Not provided | H87: Provided | I87: C&B | J87: C&B - BOQ
A88: Plotted Development at Usthi | B88: Club House - Door & Window Package | C88: 46244 | D88: 46244 | E88: 46244 | G88: Provided | H88: Provided | I88: C&B
A89: Plotted Development at Usthi | B89: Club House - External Paint | C89: 46244 | D89: 46244 | E89: 46244 | G89: Provided | H89: Provided | I89: C&P
A90: Plotted Development at Usthi | B90: Club House - Interior with Furniture | C90: 46236 | D90: 46236 | E90: 46236 | G90: Not provided | H90: Provided | I90: C&B | J90: C&B - BOQ
A91: Plotted Development at Usthi | B91: Club House - HVAC | C91: 46234 | D91: 46234 | E91: 46234 | G91: provided | H91: provided | I91: C&P
A92: Plotted Development at Usthi | B92: Banquate - External Paint | C92: 46206 | D92: 46206 | E92: 46206 | G92: Provided | H92: Provided | I92: C&P
A93: Plotted Development at Usthi | B93: Banquate - Interior with Furniture | C93: 46236 | D93: 46236 | E93: 46236 | G93: Not provided | H93: Provided | I93: C&B | J93: C&B - BOQ
A94: Raipur Plotted | B94: LANDSCAPE- Softscape | C94: 46189 | D94: 46308 | E94: 46308 | G94: Not provided | H94: NOT PROVIDED | I94: Design | J94: Design - BOQ
A95: Raipur Plotted | B95: LANDSCAPE- Hardscape | C95: 46189 | D95: 46299 | E95: 46299 | G95: Not provided | H95: Provided | I95: C&B | J95: C&B - BOQ
A96: Raipur Plotted | B96: Club House - Interior | C96: 46311 | D96: 46273 | E96: 46273 | G96: Provided | H96: Provided | I96: C&P
